splipy_core-1.10.1.dist-info/RECORD
splipy_core-1.10.1.dist-info/WHEEL
splipy_core-1.10.1.dist-info/top_level.txt
splipy_core-1.10.1.dist-info/METADATA
splipy_core/__init__.pyi
splipy_core/__init__.py
splipy_core/_core.cpython-312-darwin.so
splipy_core/core.c
splipy_core/py.typed
splipy_core/core.pyx
