Metadata-Version: 2.4
Name: splipy-core
Version: 1.10.1
Summary: Add your description here
Author-email: Eivind Fonn <evfonn@gmail.com>
Requires-Python: <4.0,>=3.11
Requires-Dist: numpy>=1.25
